tex_gen.py
tex_gen_v2-0.1.1.dist-info/METADATA
tex_gen_v2-0.1.1.dist-info/WHEEL
tex_gen_v2-0.1.1.dist-info/top_level.txt
tex_gen_v2-0.1.1.dist-info/RECORD
